ststeroids/__init__.py
ststeroids/component.py
ststeroids/flow.py
ststeroids/layout.py
ststeroids/router.py
ststeroids/store.py
ststeroids/style.py
ststeroids-0.1.17.dist-info/licenses/LICENSE
ststeroids-0.1.17.dist-info/METADATA
ststeroids-0.1.17.dist-info/WHEEL
ststeroids-0.1.17.dist-info/top_level.txt
ststeroids-0.1.17.dist-info/RECORD
