Metadata-Version: 2.4
Name: ststeroids
Version: 0.1.17
Summary: A framework supercharging Streamlit for building advanced multi-page applications
Author: ponsoc
License: MIT License
Project-URL: Homepage, https://github.com/ponsoc/ststeroids
Project-URL: Bug Reports, https://github.com/ponsoc/ststeroids/issues
Requires-Python: >=3.11.0
License-File: LICENSE
Requires-Dist: streamlit>=1.41.0
Dynamic: license-file
